example/__init__.py
example/admin.py
example/manage.py
example/models.py
example/settings.py
example/urls.py
example/views.py
example/tests/__init__.py
example/tests/conftest.py
example/tests/factories.py
example/tests/test_models.py
localizedfields/__init__.py
localizedfields/admin.py
localizedfields/fields.py
localizedfields/models.py
localizedfields/utils.py
localizedfields/locale/de/LC_MESSAGES/django.mo
localizedfields/static/localizedfields/js.cookie.min.js
localizedfields/static/localizedfields/localizedfields.css
localizedfields/static/localizedfields/localizedfields.js
django_localizedfields-0.19.dist-info/LICENSE.txt
django_localizedfields-0.19.dist-info/METADATA
django_localizedfields-0.19.dist-info/WHEEL
django_localizedfields-0.19.dist-info/top_level.txt
django_localizedfields-0.19.dist-info/RECORD
